imreadeval/__init__.py
imreadeval/imread.py
imreadeval/images/clouds.png
imreadeval/images/squirrel.jpg
imreadeval-0.2.2.dist-info/DESCRIPTION.rst
imreadeval-0.2.2.dist-info/METADATA
imreadeval-0.2.2.dist-info/RECORD
imreadeval-0.2.2.dist-info/WHEEL
imreadeval-0.2.2.dist-info/metadata.json
imreadeval-0.2.2.dist-info/top_level.txt
