Metadata-Version: 2.0
Name: imreadeval
Version: 0.2.2
Summary: An evaluation to python imread functions
Home-page: http://github.com/quxiaofeng/imreadeval
Author: QU Xiaofeng
Author-email: xiaofeng.qu@aqara.com
License: MIT license, Copyright (c) 2018 QU Xiaofeng
Platform: UNKNOWN
Classifier: Development Status :: 2 - Pre-Alpha
Classifier: Environment :: Console
Classifier: Intended Audience :: Science/Research
Classifier: License :: OSI Approved :: MIT License
Classifier: Natural Language :: English
Classifier: Natural Language :: Chinese (Simplified)
Classifier: Operating System :: Microsoft :: Windows
Classifier: Operating System :: POSIX :: Linux
Classifier: Programming Language :: Python
Classifier: Programming Language :: Python :: 2
Classifier: Programming Language :: Python :: 2.7
Classifier: Programming Language :: Python :: 3
Classifier: Programming Language :: Python :: 3.6
Classifier: Programming Language :: Python :: 3.7
Classifier: Topic :: Scientific/Engineering :: Image Recognition
Classifier: Topic :: Scientific/Engineering :: Artificial Intelligence
Requires-Dist: Pillow
Requires-Dist: pytest
